pythonvCard4/init.py
pythonvCard4/vcard.py
pythonvcard4-0.2.0.dist-info/licenses/LICENSE
pythonvcard4-0.2.0.dist-info/METADATA
pythonvcard4-0.2.0.dist-info/WHEEL
pythonvcard4-0.2.0.dist-info/top_level.txt
pythonvcard4-0.2.0.dist-info/RECORD
