Metadata-Version: 2.4
Name: pythonvCard4
Version: 0.2.0
Summary: RFC 6350-compliant vCard 4.0 parser & generator
Author-email: Sharfuddin Shawon <sharf@shawon.me>
License: MIT License
Project-URL: Homepage, https://shawon.me
Project-URL: Repository, https://github.com/sharf-shawon/pythonvCard4
Requires-Python: >=3.8
License-File: LICENSE
Dynamic: license-file
